week-2/SC3.v
module complex_circuit(A2,B2,C2,Z);
output Z;
input A2,B2,C2;
wire w1,w2,w3;
and G1(w1,B2,C2);
and G2(w2,A2,B2);
or G3(w3,A2,w1);
or G4(Z,w3,w2);
endmodule

week-2/SC3_tb.v
module tb_complex_circuit;
reg A2, B2, C2;
wire Z;
complex_circuit m1(A2,B2,C2,Z);

initial
begin
#0 A2=1'b0; B2=1'b0; C2=1'b0;
#5 A2=1'b0; B2=1'b0; C2=1'b1;
#5 A2=1'b0; B2=1'b1; C2=1'b0;
#5 A2=1'b0; B2=1'b1; C2=1'b1;
#5 A2=1'b1; B2=1'b0; C2=1'b0;
#5 A2=1'b1; B2=1'b0; C2=1'b1;
#5 A2=1'b1; B2=1'b1; C2=1'b0;
#5 A2=1'b1; B2=1'b1; C2=1'b1;
#5;
end

initial
begin
$monitor($time, " A2=%b, B2=%b, C2=%b, Z=%b", A2, B2, C2, Z);
end
initial
begin
$dumpfile ("tb_complex_circuit.vcd");
$dumpvars (0, m1);
end
endmodule

week-2/tb_complex_circuit.vcd
$date
	Sat Aug 24 21:05:58 2024
$end
$version
	Icarus Verilog
$end
$timescale
	1s
$end
$scope module tb_complex_circuit $end
$scope module m1 $end
$var wire 1 ! A2 $end
$var wire 1 " B2 $end
$var wire 1 # C2 $end
$var wire 1 $ Z $end
$var wire 1 % w1 $end
$var wire 1 & w2 $end
$var wire 1 ' w3 $end
$upscope $end
$upscope $end
$enddefinitions $end
$comment Show the parameter values. $end
$dumpall
$end
#0
$dumpvars
0'
0&
0%
0$
0#
0"
0!
$end
#5
1#
#10
0#
1"
#15
1$
1'
1%
1#
#20
0%
0#
0"
1!
#25
1#
#30
1&
0#
1"
#35
1%
1#
