week-2/SC2.v
module simple_circuit2(A,B,C,D);
output D;
input A,B,C;
wire w1;
and G1(w1,B,C);
or G2(D,A,w1);
endmodule

week-2/SC2_tb.v
module tb_simple_circuit2;
reg A, B, C;
wire D;
simple_circuit2 m1(A,B,C,D);

initial
begin
#0 A=1'b0; B=1'b0; C=1'b0;
#5 A=1'b0; B=1'b0; C=1'b1;
#5 A=1'b0; B=1'b1; C=1'b0;
#5 A=1'b0; B=1'b1; C=1'b1;
#5 A=1'b1; B=1'b0; C=1'b0;
#5 A=1'b1; B=1'b0; C=1'b1;
#5 A=1'b1; B=1'b1; C=1'b0;
#5 A=1'b1; B=1'b1; C=1'b1;
#5;
end

initial
begin
$monitor($time, " A=%b, B=%b, C=%b, D=%b", A, B, C, D);
end
initial
begin
$dumpfile ("tb_simple_circuit2.vcd");
$dumpvars(0,m1);
end
endmodule

week-2/tb_simple_circuit2.vcd
$date
	Sat Aug 24 21:01:11 2024
$end
$version
	Icarus Verilog
$end
$timescale
	1s
$end
$scope module tb_simple_circuit2 $end
$scope module m1 $end
$var wire 1 ! A $end
$var wire 1 " B $end
$var wire 1 # C $end
$var wire 1 $ D $end
$var wire 1 % w1 $end
$upscope $end
$upscope $end
$enddefinitions $end
$comment Show the parameter values. $end
$dumpall
$end
#0
$dumpvars
0%
0$
0#
0"
0!
$end
#5
1#
#10
0#
1"
#15
1$
1%
1#
#20
0%
0#
0"
1!
#25
1#
#30
0#
1"
#35
1%
1#
