week-3/full adder/full_adder.v
module fulladd(input wire a, b, cin, output wire sum, cout);
    wire [4:0] t;
    xor x0(t[0], a, b);
    xor x1(sum, t[0], cin);

    and a0(t[1], a, b);
    and a1(t[2], a, cin);
    and a2(t[3], b, cin);

    or o0(t[4], t[1], t[2]);
    or o1(cout, t[3], t[4]);
endmodule

week-3/full adder/full_adder_tb.v
module fulladd_tb;
    reg aa, bb, cc;  // Inputs to the full adder
    wire ss, cy;     // Outputs from the full adder

    // Instantiate the full adder
    fulladd add1(.a(aa), .b(bb), .cin(cc), .sum(ss), .cout(cy));

    initial begin
        $dumpfile("fulladd_test.vcd");
        $dumpvars(0, fulladd_tb);
    end

    initial begin
        $monitor($time, " a=%b, b=%b, c=%b, sum=%b, carry=%b", aa, bb, cc, ss, cy);

        // Test cases
        aa = 1'b0; bb = 1'b0; cc = 1'b0;
        #5;
        aa = 1'b0; bb = 1'b1; cc = 1'b0;
        #5;
        aa = 1'b1; bb = 1'b0; cc = 1'b0;
        #5;
        aa = 1'b1; bb = 1'b1; cc = 1'b0;
        #5;
        aa = 1'b0; bb = 1'b0; cc = 1'b1;
        #5;
        aa = 1'b0; bb = 1'b1; cc = 1'b1;
        #5;
        aa = 1'b1; bb = 1'b0; cc = 1'b1;
        #5;
        aa = 1'b1; bb = 1'b1; cc = 1'b1;
        #5;
    end
endmodule

week-3/full adder/fulladd_test.vcd
$date
	Thu Aug 29 14:28:46 2024
$end
$version
	Icarus Verilog
$end
$timescale
	1s
$end
$scope module fulladd_tb $end
$var wire 1 ! ss $end
$var wire 1 " cy $end
$var reg 1 # aa $end
$var reg 1 $ bb $end
$var reg 1 % cc $end
$scope module add1 $end
$var wire 1 # a $end
$var wire 1 $ b $end
$var wire 1 % cin $end
$var wire 1 " cout $end
$var wire 1 ! sum $end
$var wire 5 & t [4:0] $end
$upscope $end
$upscope $end
$enddefinitions $end
$comment Show the parameter values. $end
$dumpall
$end
#0
$dumpvars
b0 &
0%
0$
0#
0"
0!
$end
#5
1!
b1 &
1$
#10
0$
1#
#15
1"
0!
b10010 &
1$
#20
0"
1!
b0 &
1%
0$
0#
#25
0!
1"
b1001 &
1$
#30
1"
b10101 &
0$
1#
#35
1!
b11110 &
1$
