week-3/ripple carry adder/ripple_carry_adder.v
module fulladd(input wire a, b, cin, output wire sum, cout);
    wire [4:0] t;

    xor x0(t[0], a, b);
    xor x1(sum, t[0], cin);

    and a0(t[1], a, b);
    and a1(t[2], a, cin);
    and a2(t[3], b, cin);

    or o0(t[4], t[1], t[2]);
    or o1(cout, t[3], t[4]);
endmodule

module rca_4bit(input wire [3:0] a, b, input wire cin, output wire [3:0] sum, output wire cout);
    wire c1, c2, c3;

    fulladd fa0 (.a(a[0]), .b(b[0]), .cin(cin),  .sum(sum[0]), .cout(c1));
    fulladd fa1 (.a(a[1]), .b(b[1]), .cin(c1), .sum(sum[1]), .cout(c2));
    fulladd fa2 (.a(a[2]), .b(b[2]), .cin(c2), .sum(sum[2]), .cout(c3));
    fulladd fa3 (.a(a[3]), .b(b[3]), .cin(c3), .sum(sum[3]), .cout(cout));
endmodule

week-3/ripple carry adder/ripple_carry_adder_tb.v
module tb;
    reg [3:0] i0, i1;
    reg cin;
    wire [3:0] o;
    wire cout;
    reg [8:0] test_vecs [0:9]; 
    integer i;

    rca_4bit u0 (.a(i0), .b(i1), .cin(cin), .sum(o), .cout(cout));

    initial begin
        $dumpfile("rca_test.vcd");
        $dumpvars(0, tb);
    end

    initial begin
        test_vecs[0] = 9'b000000000;
        test_vecs[1] = 9'b000000001;
        test_vecs[2] = 9'b000100010;
        test_vecs[3] = 9'b000100011;
        test_vecs[4] = 9'b001000100;
        test_vecs[5] = 9'b001000101;
        test_vecs[6] = 9'b101010110;
        test_vecs[7] = 9'b101010111;
        test_vecs[8] = 9'b111011110;
        test_vecs[9] = 9'b111011111;
    end

    initial begin
        {i0, i1, cin} = 0;
        for (i = 0; i < 10; i = i + 1) begin
            #10 {i0, i1, cin} = test_vecs[i];
        end
        #100 $finish;
    end

    always @(i0 or i1 or cin) begin
        $monitor("At time = %t, i0=%b, i1=%b, cin=%b, Sum = %b, Carry = %b", 
                  $time, i0, i1, cin, o, cout);
    end
endmodule

week-3/ripple carry adder/rca_test.vcd
$date
	Thu Aug 29 14:59:14 2024
$end
$version
	Icarus Verilog
$end
$timescale
	1s
$end
$scope module tb $end
$var wire 4 ! o [3:0] $end
$var wire 1 " cout $end
$var reg 1 # cin $end
$var reg 4 $ i0 [3:0] $end
$var reg 4 % i1 [3:0] $end
$var integer 32 & i [31:0] $end
$scope module u0 $end
$var wire 4 ' a [3:0] $end
$var wire 4 ( b [3:0] $end
$var wire 1 # cin $end
$var wire 4 ) sum [3:0] $end
$var wire 1 " cout $end
$var wire 1 * c3 $end
$var wire 1 + c2 $end
$var wire 1 , c1 $end
$scope module fa0 $end
$var wire 1 - a $end
$var wire 1 . b $end
$var wire 1 # cin $end
$var wire 1 , cout $end
$var wire 1 / sum $end
$var wire 5 0 t [4:0] $end
$upscope $end
$scope module fa1 $end
$var wire 1 1 a $end
$var wire 1 2 b $end
$var wire 1 , cin $end
$var wire 1 + cout $end
$var wire 1 3 sum $end
$var wire 5 4 t [4:0] $end
$upscope $end
$scope module fa2 $end
$var wire 1 5 a $end
$var wire 1 6 b $end
$var wire 1 + cin $end
$var wire 1 * cout $end
$var wire 1 7 sum $end
$var wire 5 8 t [4:0] $end
$upscope $end
$scope module fa3 $end
$var wire 1 9 a $end
$var wire 1 : b $end
$var wire 1 * cin $end
$var wire 1 " cout $end
$var wire 1 ; sum $end
$var wire 5 < t [4:0] $end
$upscope $end
$upscope $end
$upscope $end
$enddefinitions $end
$comment Show the parameter values. $end
$dumpall
$end
#0
$dumpvars
b0 <
0;
0:
09
b0 8
07
06
05
b0 4
03
02
01
b0 0
0/
0.
0-
0,
0+
0*
b0 )
b0 (
b0 '
b0 &
b0 %
b0 $
0#
0"
b0 !
$end
#10
b1 &
#20
b1 !
b1 )
1/
b10 &
1#
#30
13
1,
b10010 0
1-
1.
b10 !
b10 )
0/
b11 &
b1 $
b1 '
b1 %
b1 (
0#
#40
b11 !
b11 )
1/
b11110 0
b100 &
1#
#50
03
0,
17
1+
b10010 4
0-
11
0.
12
b100 !
b100 )
0/
b0 0
b101 &
b10 $
b10 '
b10 %
b10 (
0#
#60
b101 !
b101 )
1/
b110 &
1#
#70
1"
b1 0
b10010 <
19
1.
1:
b101 !
b101 )
1/
b111 &
b1010 $
b1010 '
b1011 %
b1011 (
0#
#80
13
b11110 4
1,
b110 !
b110 )
0/
b1001 0
b1000 &
1#
#90
1;
b11110 <
1*
03
b10010 4
0,
b11110 8
15
16
b1101 !
b1101 )
1/
b1 0
b1001 &
b1110 $
b1110 '
b1111 %
b1111 (
0#
#100
13
b11110 4
1,
b1110 !
b1110 )
0/
b1001 0
b1010 &
1#
